hipocap/__init__.py
hipocap/api_client.py
hipocap/cli/__init__.py
hipocap/cli/datasets.py
hipocap/cli/evals.py
hipocap/cli/rules.py
hipocap/client.py
hipocap/config.py
hipocap/decorators.py
hipocap/exceptions.py
hipocap/hipocap.py
hipocap/types.py
hipocap-0.0.4b0.dist-info/WHEEL
hipocap-0.0.4b0.dist-info/entry_points.txt
hipocap-0.0.4b0.dist-info/METADATA
hipocap-0.0.4b0.dist-info/RECORD
