Metadata-Version: 2.4
Name: hipocap
Version: 0.0.4b0
Summary: Python SDK for Hipocap
Author: hipocap.com
Author-email: hipocap.com <admin@hipocap.com>
License-Expression: Apache-2.0
Classifier: License :: OSI Approved :: Apache Software License
Classifier: Programming Language :: Python :: 3
Classifier: Programming Language :: Python :: 3.10
Classifier: Programming Language :: Python :: 3.11
Classifier: Programming Language :: Python :: 3.12
Classifier: Programming Language :: Python :: 3.13
Classifier: Programming Language :: Python :: 3.14
Requires-Dist: lmnr>=0.7.30
Requires-Dist: pydantic>=2.0.3,<3.0.0
Requires-Dist: python-dotenv>=1.0
Requires-Dist: opentelemetry-api>=1.33.0
Requires-Dist: opentelemetry-sdk>=1.33.0
Requires-Dist: opentelemetry-exporter-otlp-proto-http>=1.33.0
Requires-Dist: opentelemetry-exporter-otlp-proto-grpc>=1.33.0
Requires-Dist: opentelemetry-instrumentation>=0.54b0
Requires-Dist: opentelemetry-semantic-conventions>=0.54b0
Requires-Dist: opentelemetry-semantic-conventions-ai>=0.4.13
Requires-Dist: tqdm>=4.0
Requires-Dist: tenacity>=8.0
Requires-Dist: grpcio>=1
Requires-Dist: httpx>=0.24.0
Requires-Dist: orjson>=3.0.0
Requires-Dist: packaging>=22.0
Requires-Dist: opentelemetry-instrumentation-threading>=0.57b0
Requires-Dist: opentelemetry-instrumentation-alephalpha>=0.47.1 ; extra == 'alephalpha'
Requires-Dist: opentelemetry-instrumentation-alephalpha>=0.47.1 ; extra == 'all'
Requires-Dist: opentelemetry-instrumentation-bedrock>=0.47.1 ; extra == 'all'
Requires-Dist: opentelemetry-instrumentation-chromadb>=0.47.1 ; extra == 'all'
Requires-Dist: opentelemetry-instrumentation-cohere>=0.47.1 ; extra == 'all'
Requires-Dist: opentelemetry-instrumentation-crewai>=0.47.1 ; extra == 'all'
Requires-Dist: opentelemetry-instrumentation-haystack>=0.47.1 ; extra == 'all'
Requires-Dist: opentelemetry-instrumentation-lancedb>=0.47.1 ; extra == 'all'
Requires-Dist: opentelemetry-instrumentation-langchain>=0.47.1,<0.48.0 ; extra == 'all'
Requires-Dist: opentelemetry-instrumentation-llamaindex>=0.47.1 ; extra == 'all'
Requires-Dist: opentelemetry-instrumentation-marqo>=0.47.1 ; extra == 'all'
Requires-Dist: opentelemetry-instrumentation-mcp>=0.47.1 ; extra == 'all'
Requires-Dist: opentelemetry-instrumentation-milvus>=0.47.1 ; extra == 'all'
Requires-Dist: opentelemetry-instrumentation-mistralai>=0.47.1 ; extra == 'all'
Requires-Dist: opentelemetry-instrumentation-ollama>=0.47.1 ; extra == 'all'
Requires-Dist: opentelemetry-instrumentation-pinecone>=0.47.1 ; extra == 'all'
Requires-Dist: opentelemetry-instrumentation-qdrant>=0.47.1 ; extra == 'all'
Requires-Dist: opentelemetry-instrumentation-replicate>=0.47.1 ; extra == 'all'
Requires-Dist: opentelemetry-instrumentation-sagemaker>=0.47.1 ; extra == 'all'
Requires-Dist: opentelemetry-instrumentation-together>=0.47.1 ; extra == 'all'
Requires-Dist: opentelemetry-instrumentation-transformers>=0.47.1 ; extra == 'all'
Requires-Dist: opentelemetry-instrumentation-vertexai>=0.47.1 ; extra == 'all'
Requires-Dist: opentelemetry-instrumentation-watsonx>=0.47.1 ; extra == 'all'
Requires-Dist: opentelemetry-instrumentation-weaviate>=0.47.1 ; extra == 'all'
Requires-Dist: opentelemetry-instrumentation-bedrock>=0.47.1 ; extra == 'bedrock'
Requires-Dist: opentelemetry-instrumentation-chromadb>=0.47.1 ; extra == 'chromadb'
Requires-Dist: hipocap-claude-code-proxy>=0.1.5 ; extra == 'claude-agent-sdk'
Requires-Dist: opentelemetry-instrumentation-cohere>=0.47.1 ; extra == 'cohere'
Requires-Dist: opentelemetry-instrumentation-crewai>=0.47.1 ; extra == 'crewai'
Requires-Dist: opentelemetry-instrumentation-haystack>=0.47.1 ; extra == 'haystack'
Requires-Dist: opentelemetry-instrumentation-lancedb>=0.47.1 ; extra == 'lancedb'
Requires-Dist: opentelemetry-instrumentation-langchain>=0.47.1,<0.48.0 ; extra == 'langchain'
Requires-Dist: opentelemetry-instrumentation-llamaindex>=0.47.1 ; extra == 'llamaindex'
Requires-Dist: opentelemetry-instrumentation-marqo>=0.47.1 ; extra == 'marqo'
Requires-Dist: opentelemetry-instrumentation-mcp>=0.47.1 ; extra == 'mcp'
Requires-Dist: opentelemetry-instrumentation-milvus>=0.47.1 ; extra == 'milvus'
Requires-Dist: opentelemetry-instrumentation-mistralai>=0.47.1 ; extra == 'mistralai'
Requires-Dist: opentelemetry-instrumentation-ollama>=0.47.1 ; extra == 'ollama'
Requires-Dist: opentelemetry-instrumentation-pinecone>=0.47.1 ; extra == 'pinecone'
Requires-Dist: opentelemetry-instrumentation-qdrant>=0.47.1 ; extra == 'qdrant'
Requires-Dist: opentelemetry-instrumentation-replicate>=0.47.1 ; extra == 'replicate'
Requires-Dist: opentelemetry-instrumentation-sagemaker>=0.47.1 ; extra == 'sagemaker'
Requires-Dist: opentelemetry-instrumentation-together>=0.47.1 ; extra == 'together'
Requires-Dist: opentelemetry-instrumentation-transformers>=0.47.1 ; extra == 'transformers'
Requires-Dist: opentelemetry-instrumentation-vertexai>=0.47.1 ; extra == 'vertexai'
Requires-Dist: opentelemetry-instrumentation-watsonx>=0.47.1 ; extra == 'watsonx'
Requires-Dist: opentelemetry-instrumentation-weaviate>=0.47.1 ; extra == 'weaviate'
Requires-Python: >=3.10, <4
Provides-Extra: alephalpha
Provides-Extra: all
Provides-Extra: bedrock
Provides-Extra: chromadb
Provides-Extra: claude-agent-sdk
Provides-Extra: cohere
Provides-Extra: crewai
Provides-Extra: haystack
Provides-Extra: lancedb
Provides-Extra: langchain
Provides-Extra: llamaindex
Provides-Extra: marqo
Provides-Extra: mcp
Provides-Extra: milvus
Provides-Extra: mistralai
Provides-Extra: ollama
Provides-Extra: pinecone
Provides-Extra: qdrant
Provides-Extra: replicate
Provides-Extra: sagemaker
Provides-Extra: together
Provides-Extra: transformers
Provides-Extra: vertexai
Provides-Extra: watsonx
Provides-Extra: weaviate
